ippe/__init__.py
ippe/homo2d.py
ippe/ippe.py
ippe-0.0.1.dist-info/DESCRIPTION.rst
ippe-0.0.1.dist-info/METADATA
ippe-0.0.1.dist-info/RECORD
ippe-0.0.1.dist-info/WHEEL
ippe-0.0.1.dist-info/entry_points.txt
ippe-0.0.1.dist-info/metadata.json
ippe-0.0.1.dist-info/top_level.txt
